gordon/__init__.py
gordon/actions.py
gordon/bin.py
gordon/core.py
gordon/exceptions.py
gordon/protocols.py
gordon/utils.py
gordon/utils_tests.py
gordon/contrib/__init__.py
gordon/contrib/helpers/__init__.py
gordon/contrib/helpers/resources.py
gordon/contrib/helpers/settings.yml
gordon/contrib/helpers/tests.py
gordon/contrib/helpers/sleep/__init__.py
gordon/contrib/helpers/sleep/requirements.txt
gordon/contrib/helpers/sleep/sleep.py
gordon/contrib/lambdas/__init__.py
gordon/contrib/lambdas/resources.py
gordon/contrib/lambdas/settings.yml
gordon/contrib/lambdas/tests.py
gordon/contrib/lambdas/version/__init__.py
gordon/contrib/lambdas/version/requirements.txt
gordon/contrib/lambdas/version/version.py
gordon/contrib/s3/__init__.py
gordon/contrib/s3/resources.py
gordon/contrib/s3/settings.yml
gordon/contrib/s3/tests.py
gordon/contrib/s3/bucket_notification_configuration/__init__.py
gordon/contrib/s3/bucket_notification_configuration/bucket_notification_configuration.py
gordon/contrib/s3/bucket_notification_configuration/requirements.txt
gordon/defaults/app_java/settings.yml
gordon/defaults/app_java/helloworld/build.gradle
gordon/defaults/app_java/helloworld/src/main/java/helloworld/Hello.java
gordon/defaults/app_js/settings.yml
gordon/defaults/app_js/helloworld/code.js
gordon/defaults/app_py/settings.yml
gordon/defaults/app_py/helloworld/code.py
gordon/defaults/project/settings.yml
gordon/loaders/node.js
gordon/loaders/python.py
gordon/loaders/java/build/libs/java.jar
gordon/resources/__init__.py
gordon/resources/apigateway.py
gordon/resources/base.py
gordon/resources/contexts.py
gordon/resources/dynamodb.py
gordon/resources/events.py
gordon/resources/kinesis.py
gordon/resources/lambdas.py
gordon/resources/s3.py
gordon/resources/vpcs.py
gordon-0.7.0.dist-info/DESCRIPTION.rst
gordon-0.7.0.dist-info/METADATA
gordon-0.7.0.dist-info/RECORD
gordon-0.7.0.dist-info/WHEEL
gordon-0.7.0.dist-info/entry_points.txt
gordon-0.7.0.dist-info/metadata.json
gordon-0.7.0.dist-info/pbr.json
gordon-0.7.0.dist-info/top_level.txt
