Metadata-Version: 2.0
Name: gordon
Version: 0.7.0
Summary: Gordon is a tool to create, wire and deploy AWS Lambdas using CloudFormation
Home-page: http://github.com/jorgebastida/gordon
Author: Jorge Bastida
Author-email: me@jorgebastida.com
License: BSD
Keywords: aws lambda apigateway kinesis dynamodb s3 cloudwatch
Platform: any
Classifier: Programming Language :: Python :: 3
Classifier: Programming Language :: Python :: 2
Classifier: Development Status :: 4 - Beta
Classifier: Environment :: Web Environment
Classifier: Intended Audience :: Developers
Classifier: License :: OSI Approved :: BSD License
Classifier: Operating System :: OS Independent
Classifier: Topic :: Utilities
Requires-Dist: boto3 (>=1.2.3,<2.0)
Requires-Dist: clint (>0.5,<1.0)
Requires-Dist: PyYAML (>=3,<4.0)
Requires-Dist: troposphere (>=1.6)
Requires-Dist: Jinja2 (<3.0,>=2.8)
Requires-Dist: six (>1.9,<2.0)
